<annotation>
	<folder>train</folder>
	<filename>google_0006.png</filename>
	<path>/home/eco/code/python/AutoCrawler/garden_data/train/google_0006.png</path>
	<source>
		<database>Unknown</database>
	</source>
	<size>
		<width>560</width>
		<height>315</height>
		<depth>3</depth>
	</size>
	<segmented>0</segmented>
	<object>
		<name>tree</name>
		<pose>Unspecified</pose>
		<truncated>0</truncated>
		<difficult>0</difficult>
		<bndbox>
			<xmin>227</xmin>
			<ymin>25</ymin>
			<xmax>388</xmax>
			<ymax>251</ymax>
		</bndbox>
	</object>
	<object>
		<name>tree</name>
		<pose>Unspecified</pose>
		<truncated>0</truncated>
		<difficult>0</difficult>
		<bndbox>
			<xmin>395</xmin>
			<ymin>87</ymin>
			<xmax>520</xmax>
			<ymax>236</ymax>
		</bndbox>
	</object>
	<object>
		<name>bush</name>
		<pose>Unspecified</pose>
		<truncated>1</truncated>
		<difficult>0</difficult>
		<bndbox>
			<xmin>1</xmin>
			<ymin>176</ymin>
			<xmax>85</xmax>
			<ymax>239</ymax>
		</bndbox>
	</object>
	<object>
		<name>bush</name>
		<pose>Unspecified</pose>
		<truncated>0</truncated>
		<difficult>0</difficult>
		<bndbox>
			<xmin>202</xmin>
			<ymin>231</ymin>
			<xmax>424</xmax>
			<ymax>269</ymax>
		</bndbox>
	</object>
</annotation>
